apilmoji/__init__.py
apilmoji/core.py
apilmoji/ds.py
apilmoji/helper.py
apilmoji/source.py
apilmoji-0.2.4.dist-info/WHEEL
apilmoji-0.2.4.dist-info/METADATA
apilmoji-0.2.4.dist-info/RECORD
