Metadata-Version: 2.3
Name: apilmoji
Version: 0.2.4
Summary: Pilmoji for nonebot-plugin-parser
Requires-Dist: aiofiles>=25.1.0
Requires-Dist: emoji>=2.15.0,<3.0.0
Requires-Dist: httpx>=0.27.2,<1.0.0
Requires-Dist: pillow>=11.0.0
Requires-Dist: tqdm>=4.66.0 ; extra == 'tqdm'
Requires-Python: >=3.10
Project-URL: IssueTracker, https://github.com/fllesser/apilmoji/issues
Project-URL: Release, https://github.com/fllesser/apilmoji/releases
Project-URL: Repository, https://github.com/fllesser/apilmoji
Provides-Extra: tqdm
